pmdsky_debug_py/__init__.py
pmdsky_debug_py/_release.py
pmdsky_debug_py/eu.py
pmdsky_debug_py/eu_itcm.py
pmdsky_debug_py/jp.py
pmdsky_debug_py/jp_itcm.py
pmdsky_debug_py/na.py
pmdsky_debug_py/na_itcm.py
pmdsky_debug_py/protocol.py
pmdsky_debug_py/py.typed
pmdsky_debug_py-10.2.26.dist-info/METADATA
pmdsky_debug_py-10.2.26.dist-info/WHEEL
pmdsky_debug_py-10.2.26.dist-info/top_level.txt
pmdsky_debug_py-10.2.26.dist-info/RECORD
