Metadata-Version: 2.4
Name: pmdsky-debug-py
Version: 10.2.26
Summary: pmdsky-debug symbols for Python.
Author-email: Marco 'Capypara' Köpcke <hello@capypara.de>
License: MIT
Project-URL: repository, https://github.com/SkyTemple/pmdsky-debug-py
Classifier: Development Status :: 4 - Beta
Classifier: License :: OSI Approved :: MIT License
Classifier: Programming Language :: Python :: 3.10
Classifier: Programming Language :: Python :: 3.11
Classifier: Programming Language :: Python :: 3.12
Classifier: Programming Language :: Python :: 3.13
Classifier: Programming Language :: Python
Requires-Python: >=3.10
